parent/PackageContent.py
parent/__init__.py
parent/pyarmor_runtime_005203/__init__.py
parent/pyarmor_runtime_005203/pyarmor_runtime.so
mypackagelicenseprototype-5.2.0.dist-info/METADATA
mypackagelicenseprototype-5.2.0.dist-info/WHEEL
mypackagelicenseprototype-5.2.0.dist-info/top_level.txt
mypackagelicenseprototype-5.2.0.dist-info/RECORD
