Metadata-Version: 2.1
Name: mypackagelicenseprototype
Version: 5.2.0
Requires-Dist: numpy
Requires-Dist: scipy
Requires-Dist: libpython
